{"data":[{"lista":"LISTA N\u00ba 14 \"AUTOCONVOCADOS\"                                                              ","sigla_lista":"L14 AUTO     ","total":70,"NQN M1*":70},{"lista":"LISTA N\u00ba 25 \"Frente Estudiantil\" (APE-Independientes)                                     ","sigla_lista":"L25 FEST     ","total":374,"NQN M1*":374},{"lista":"LISTA N\u00ba 30 \"LA JAURETCHE Corriente Estudiantil\"                                          ","sigla_lista":"L30 LJAU     ","total":49,"NQN M1*":49},{"lista":"Blancos","total":74,"NQN M1*":74},{"lista":"Nulos","total":5,"NQN M1*":5},{"lista":"Recurridos","total":0,"NQN M1*":0},{"lista":"Votantes","total":572,"NQN M1*":572},{"lista":"Empadronados","total":992,"NQN M1*":992}],"labels":["L14 AUTO     ","L25 FEST     ","L30 LJAU     "],"total":[70,374,49],"columns":[{"field":"lista","title":"Listas"},{"field":"sigla_lista","title":"Sigla"},{"field":"NQN M1*","title":"NQN M1*"},{"field":"total","title":"Total"}],"data2":[{"lista":"L14 AUTO     ","escanos":0,"1":70,"2":35,"3":23.33,"4":17.5},{"lista":"L25 FEST     ","escanos":4,"1":"(1)374","2":"(2)187","3":"(3)124.67","4":"(4)93.5"},{"lista":"L30 LJAU     ","escanos":0,"1":49,"2":24.5,"3":16.33,"4":12.25}],"columns2":[{"field":"lista","title":"Listas"},{"field":"escanos","title":"Cargos"},{"field":1,"title":1},{"field":2,"title":2},{"field":3,"title":3},{"field":4,"title":4}],"titulo2":"Distribuci\u00f3n de cargos a ocupar","fecha":"20\/05\/2018 4:01:26","titulo":"Votos FAEA Consejero Directivo Estudiantes ","enviadas":"100% (1 de 1)","confirmadas":"100% (1 de 1)"}