{"columns":[{"field":"lista","title":"Listas"},{"field":"sigla_lista","title":"Sigla Listas"},{"field":"NQN mesa 1","title":"NQN mesa 1"},{"field":"NQN mesa 2","title":"NQN mesa 2"},{"field":"ZAP mesa 1","title":"ZAP mesa 1"},{"field":"total","title":"Total"}],"data":[{"lista":"LISTA N\u00b013: \"EPPUR SI MUOVE INGENIERIA\"","sigla_lista":"L\"EPPUR","NQN mesa 1":101,"NQN mesa 2":66,"ZAP mesa 1":4,"total":"171"},{"lista":"LISTA N\u00b020: \"FEM- FUERZA ESTUDIANTIL EN MOVIMIENTO\"","sigla_lista":"L\"FEM- F","NQN mesa 1":80,"NQN mesa 2":57,"ZAP mesa 1":3,"total":"140"},{"lista":"LISTA N\u00b08: \"UNIDAD POR INGENIERIA (CEPA + INDEPENDIENTES)\"","sigla_lista":"L\"UNIDAD","NQN mesa 1":195,"NQN mesa 2":146,"ZAP mesa 1":2,"total":"343"}],"labels":["L\"EPPUR   ","L\"FEM- F  ","L\"UNIDAD  "],"total":["171","140","343"],"fecha":"14\/05\/2018 19:37:01","titulo":"Votos FAIN Consejero Directivo Estudiantes "}