{"columns":[{"field":"lista","title":"Listas"},{"field":"sigla_lista","title":"Sigla Listas"},{"field":"GRO mesa 3","title":"GRO mesa 3"},{"field":"GRO mesa 2","title":"GRO mesa 2"},{"field":"GRO mesa 1","title":"GRO mesa 1"},{"field":"NQN mesa 1","title":"NQN mesa 1"},{"field":"total","title":"Total"}],"data":[{"lista":"LISTA N\u00b01: \"FRENTE DE ESTUDIANTES POR COMAHUE\"","sigla_lista":"FEC","GRO mesa 3":24,"GRO mesa 2":25,"GRO mesa 1":12,"NQN mesa 1":3,"total":"64"},{"lista":"LISTA N\u00b02: \"FRENTE DE ESTUDIANTES INDEPENDIENTES\"","sigla_lista":"FEI","GRO mesa 3":12,"GRO mesa 2":10,"GRO mesa 1":8,"NQN mesa 1":3,"total":"33"},{"lista":"LISTA N\u00b03: \"LA JUNTADA AUCA PIUKE + LA MELLA + INDEPENDIENTES\"","sigla_lista":"JAPLMI","GRO mesa 3":23,"GRO mesa 1":30,"GRO mesa 2":32,"NQN mesa 1":2,"total":"87"},{"lista":"LISTA N\u00b04: \"UNIDAD ESTUDIANTIL ECU\" (CEPA + INDEPENDIENTES)","sigla_lista":"ECU","GRO mesa 2":31,"GRO mesa 1":30,"GRO mesa 3":22,"NQN mesa 1":3,"total":"86"},{"lista":"LISTA N\u00b05: \"COMPROMISO UNIVERSITARIO\"","sigla_lista":"CUE","GRO mesa 1":16,"GRO mesa 3":8,"GRO mesa 2":7,"NQN mesa 1":4,"total":"35"},{"lista":"LISTA N\u00b06: \"LA IZQUIERDA AL FRENTE (PTS-NUEVO MAS)\"","sigla_lista":"LIF","GRO mesa 3":5,"GRO mesa 2":5,"GRO mesa 1":11,"NQN mesa 1":7,"total":"28"},{"lista":"LISTA N\u00b07: \"MILES + LA FUENTEALBA + LA ALAMEDA\"","sigla_lista":"MLFLA","GRO mesa 2":46,"GRO mesa 1":50,"GRO mesa 3":46,"NQN mesa 1":1,"total":"143"},{"lista":"LISTA N\u00b08: \"MST NUEVA IZQUIERDA\"","sigla_lista":"MSTNI","GRO mesa 1":2,"GRO mesa 3":2,"GRO mesa 2":3,"NQN mesa 1":2,"total":"9"}],"labels":["FEC       ","FEC       ","FEC       ","FEC       ","FEI       ","FEI       ","FEI       ","FEI       ","JAPLMI    ","JAPLMI    ","JAPLMI    ","JAPLMI    ","ECU       ","ECU       ","ECU       ","ECU       ","CUE       ","CUE       ","CUE       ","CUE       ","LIF       ","LIF       ","LIF       ","LIF       ","MLFLA     ","MLFLA     ","MLFLA     ","MLFLA     ","MSTNI     ","MSTNI     ","MSTNI     ","MSTNI     "],"total":["64","64","64","64","33","33","33","33","87","87","87","87","86","86","86","86","35","35","35","35","28","28","28","28","143","143","143","143","9","9","9","9"],"fecha":"13\/05\/2018 23:49:12","titulo":"Votos FADE Consejero Superior Estudiantes "}