{"data":[{"lista":"LISTA N\u00ba 1: REUNCO                                                              ","sigla_lista":"L1 REUNCO    ","total":1,"BHE M1*":1},{"lista":"LISTA N\u00ba 2: LISTA CELESTE Y BLANCA                                              ","sigla_lista":"L2 LCYB      ","total":1,"BHE M1*":1},{"lista":"LISTA N\u00ba 3: UNIDAD INDEPENDIENTE DE TRABAJADORES                                ","sigla_lista":"L3 UNIT      ","total":11,"BHE M1*":11},{"lista":"LISTA N\u00ba 4: TRABAJADORES EN LUCHA                                               ","sigla_lista":"L4 TELU      ","total":8,"BHE M1*":8},{"lista":"LISTA N\u00ba 5: LISTA BLANCA UNIDAD GREMIAL                                         ","sigla_lista":"L5 LBUG      ","total":6,"BHE M1*":6},{"lista":"Blancos","total":2,"BHE M1*":2},{"lista":"Nulos","total":0,"BHE M1*":0},{"lista":"Recurridos","total":0,"BHE M1*":0},{"lista":"Votantes","total":29,"BHE M1*":29},{"lista":"Empadronados","total":33,"BHE M1*":33}],"labels":["L1 REUNCO    ","L2 LCYB      ","L3 UNIT      ","L4 TELU      ","L5 LBUG      "],"total":[1,1,11,8,6],"columns":[{"field":"lista","title":"Listas"},{"field":"sigla_lista","title":"Sigla"},{"field":"BHE M1*","title":"BHE M1*"},{"field":"total","title":"Total"}],"fecha":"02\/06\/2018 10:11:11","titulo":"Votos CRUB Consejero Superior No docente  ","enviadas":"100% (1 de 1)","confirmadas":"100% (1 de 1)"}