{"data":[{"lista":"LISTA N\u00ba26:  \"JUNTOS POR AGRARIAS\"                                                        ","sigla_lista":"L26 JPAG     ","total":16,"CSA M1*":10,"SMA M1*":6},{"lista":"LISTA N\u00ba 27: \"ECU AGRARIAS\"                                                               ","sigla_lista":"L27 ECUA     ","total":16,"CSA M1*":16,"SMA M1*":0},{"lista":"Blancos","total":6,"CSA M1*":6,"SMA M1*":0},{"lista":"Nulos","total":2,"CSA M1*":2,"SMA M1*":0},{"lista":"Recurridos","total":0,"CSA M1*":0,"SMA M1*":0},{"lista":"Votantes","total":40,"CSA M1*":34,"SMA M1*":6},{"lista":"Empadronados","total":40,"CSA M1*":34,"SMA M1*":6}],"labels":["L26 JPAG     ","L27 ECUA     "],"total":[16,16],"columns":[{"field":"lista","title":"Listas"},{"field":"sigla_lista","title":"Sigla"},{"field":"CSA M1*","title":"CSA M1*"},{"field":"SMA M1*","title":"SMA M1*"},{"field":"total","title":"Total"}],"fecha":"02\/06\/2018 10:11:11","titulo":"Votos FACA Decano No docente  ","enviadas":"100% (2 de 2)","confirmadas":"100% (2 de 2)"}