{"data":[{"lista":"LISTA N\u00ba 1: \"CONVERGENCIA UNIVERSITARIA\"                                        ","sigla_lista":"L1 CRISAFULLI","total":93,"NQN M1*":93},{"lista":"LISTA N\u00ba 2: \"MOVIMIENTO ACADEMICO INTERCLAUSTRO\"                                ","sigla_lista":"L2 VAUCHERET ","total":11,"NQN M1*":11},{"lista":"LISTA N\u00ba 3: \"CONSTRUIR\"                                                         ","sigla_lista":"L3 GIULIANI  ","total":81,"NQN M1*":81},{"lista":"LISTA N\u00ba 4: \"PLURALISMO E INSTITUCIONALIDAD\"                                    ","sigla_lista":"L4 BRAMARDI  ","total":34,"NQN M1*":34},{"lista":"LISTA N\u00ba 5: \"ENCUENTRO PARA CAMBIAR  LA UNCo - ECU\"                             ","sigla_lista":"L5 TRPIN     ","total":20,"NQN M1*":20},{"lista":"Blancos","total":9,"NQN M1*":9},{"lista":"Nulos","total":4,"NQN M1*":4},{"lista":"Recurridos","total":0,"NQN M1*":0},{"lista":"Votantes","total":252,"NQN M1*":252},{"lista":"Empadronados","total":275,"NQN M1*":275}],"labels":["L1 CRISAFULLI","L2 VAUCHERET ","L3 GIULIANI  ","L4 BRAMARDI  ","L5 TRPIN     "],"total":[93,11,81,34,20],"columns":[{"field":"lista","title":"Listas"},{"field":"sigla_lista","title":"Sigla"},{"field":"NQN M1*","title":"NQN M1*"},{"field":"total","title":"Total"}],"fecha":"02\/06\/2018 10:11:11","titulo":"Votos RECT Rector No docente  ","enviadas":"100% (1 de 1)","confirmadas":"100% (1 de 1)"}